pyloans/Loan.py
pyloans/__init__.py
pyloans-0.1.3.dist-info/LICENSE
pyloans-0.1.3.dist-info/WHEEL
pyloans-0.1.3.dist-info/METADATA
pyloans-0.1.3.dist-info/RECORD
