Metadata-Version: 2.1
Name: pyloans
Version: 0.1.3
Summary: A package to generate, analyze and work with simple installment loans.
License: MIT
Author: Sandeep
Author-email: sandeep.kavadi.uc@gmail.com
Requires-Python: >=3.7.1,<4.0.0
Classifier: License :: OSI Approved :: MIT License
Classifier: Programming Language :: Python :: 3
Classifier: Programming Language :: Python :: 3.8
Classifier: Programming Language :: Python :: 3.9
Classifier: Programming Language :: Python :: 3.10
Classifier: Programming Language :: Python :: 3.11
Requires-Dist: numpy-financial (>=1.0.0,<2.0.0)
Requires-Dist: pandas (>1.3)
